MANIFEST.in
README.md
requirements.txt
setup.py
test/test_zcs.py
zcs/__info__.py
zcs/__init__.py
zcs/config.py
zcs/type.py
zcs.egg-info/PKG-INFO
zcs.egg-info/SOURCES.txt
zcs.egg-info/dependency_links.txt
zcs.egg-info/requires.txt
zcs.egg-info/top_level.txt