Metadata-Version: 2.1
Name: zcs
Version: 0.1.20
Summary: Z Configuration System: a flexible powerful configuration system which takes advantage of both argparse and yacs
Home-page: https://github.com/DIYer22/zcs
Author: DIYer22
Author-email: ylxx@live.com
License: UNKNOWN
Platform: UNKNOWN
Classifier: Topic :: Software Development :: Libraries :: Python Modules
Classifier: Programming Language :: Python :: 3
Classifier: License :: OSI Approved :: MIT License
Classifier: Operating System :: OS Independent
Classifier: Intended Audience :: Developers
Classifier: Intended Audience :: Science/Research
